{"derivation":"from G1909 (ἐπιφέρω) and G5342 (ἐπιφέρω);","kjv_def":"add, bring (against), take","lemma":"ἐπιφέρω","frequency":2,"strongs_def":" to bear upon (or further), i.e. adduce (personally or judicially (accuse, inflict)), superinduce","outline":"<ol><li> to bring upon, bring forward<ol><li> used of accusers</li></ol><li> to lay upon, to inflict</li><li> to bring upon, i.e. in addition, to add, increase</li><li> to put upon, cast upon, impose</li></ol>","xlit":"epiphérō","pron":"ep-ee-fer'-o"}