{"derivation":"a prolonged form of the feminine of G3432 (μοιχαλίς);","kjv_def":"adulteress(-ous, -y)","lemma":"μοιχαλίς","frequency":7,"strongs_def":" an adulteress (literally or figuratively)","outline":"<ol><li> an adulteress</li><li> as the intimate alliance of God with the people of Israel was likened to a marriage, those who relapse into idolatry are said to commit adultery or play the harlot<ol><li> fig. equiv. to faithless to God, unclean, apostate</li></ol></li></ol>","xlit":"moichalís","pron":"moy-khal-is'"}