{"derivation":"a prolonged form of an apparently primary verb (, to slur);","kjv_def":"have joy","lemma":"ὀνίνημι","frequency":1,"strongs_def":" for which another prolonged form () is used as an alternate in some tenses (unless indeed it be identical with the base of G3686 (ὀνίνημι) through the idea of notoriety); to gratify, i.e. (middle voice) to derive pleasure or advantage from","outline":"<ol><li> to be useful, to profit, help</li><li> to receive profit or advantage, be helped [or have joy]</li></ol>","xlit":"onínēmi","pron":"on-in'-ay-mee"}