{"derivation":"from G4314 (προστίθημι) and G5087 (προστίθημι);","kjv_def":"add, again, give more, increase, lay unto, proceed further, speak to any more","lemma":"προστίθημι","frequency":18,"strongs_def":" to place additionally, i.e. lay beside, annex, repeat","outline":"<ol><li> to put to</li><li> to add<ol><li> i.e. to join to, gather with any company, the number of one's followers or companions<ol><li> he was gathered to his fathers i.e. died</li></ol></li></ol></li></ol>","xlit":"prostíthēmi","pron":"pros-tith'-ay-mee"}